Metadata-Version: 2.1
Name: ethome-ml
Version: 0.6.2
Summary: Tools for machine learning of animal behavior.
Home-page: https://github.com/benlansdell/ethome
Author: Ben Lansdell
Author-email: ben.lansdell@gmail.com
Project-URL: Bug Tracker, https://github.com/benlansdell/ethome/issues
Classifier: Programming Language :: Python :: 3
Classifier: License :: OSI Approved :: MIT License
Classifier: Operating System :: OS Independent
Requires-Python: >=3.8
License-File: LICENSE
Requires-Dist: numpy
Requires-Dist: pandas
Requires-Dist: scikit-learn
Requires-Dist: tqdm
Requires-Dist: typeguard
Requires-Dist: typing
Requires-Dist: matplotlib
Requires-Dist: scikit-image
Requires-Dist: umap-learn
Requires-Dist: dill
Requires-Dist: pynwb
Requires-Dist: ipywidgets
